thumbor_video_engine/__init__.py
thumbor_video_engine/app.py
thumbor_video_engine/compat.py
thumbor_video_engine/exceptions.py
thumbor_video_engine/ffprobe.py
thumbor_video_engine/utils.py
thumbor_video_engine/engines/__init__.py
thumbor_video_engine/engines/ffmpeg.py
thumbor_video_engine/engines/gif.py
thumbor_video_engine/engines/video.py
thumbor_video_engine/filters/__init__.py
thumbor_video_engine/filters/format.py
thumbor_video_engine/filters/lossless.py
thumbor_video_engine/filters/still.py
thumbor_video_engine/filters/tune.py
thumbor_video_engine/result_storages/__init__.py
thumbor_video_engine/result_storages/aws_storage.py
thumbor_video_engine/result_storages/base.py
thumbor_video_engine/result_storages/file_storage.py
thumbor_video_engine/result_storages/s3_storage.py
thumbor_video_engine-1.2.5.dist-info/LICENSE
thumbor_video_engine-1.2.5.dist-info/METADATA
thumbor_video_engine-1.2.5.dist-info/WHEEL
thumbor_video_engine-1.2.5.dist-info/top_level.txt
thumbor_video_engine-1.2.5.dist-info/RECORD
