Metadata-Version: 2.1
Name: thumbor-video-engine
Version: 1.2.5
Summary: An engine and tools for manipulating videos with thumbor using ffmpeg
Home-page: https://github.com/theatlantic/thumbor-video-engine
Author: Frankie Dintino
Author-email: fdintino@gmail.com
Classifier: Development Status :: 5 - Production/Stable
Classifier: Intended Audience :: Developers
Classifier: Topic :: Software Development
Classifier: Environment :: Web Environment
Classifier: License :: OSI Approved :: BSD License
Classifier: Programming Language :: Python :: 2
Classifier: Programming Language :: Python :: 2.7
License-File: LICENSE
Requires-Dist: thumbor
